rtl/pe.sv
// rtl/pe.sv
module pe #(
    parameter int ACC_W = 32
) (
    input  logic                 clk,
    input  logic                 reset,   
    input  logic                 en,     

    input  logic signed [7:0]     a_in,
    input  logic signed [7:0]     b_in,

    output logic signed [7:0]     a_out,
    output logic signed [7:0]     b_out,

    output logic signed [ACC_W-1:0] acc_out
);

    // Internal register
    logic signed [ACC_W-1:0] acc_reg;

    // Compute product as signed 16-bit
    logic signed [15:0] product;
    assign product = a_in * b_in; 

    always_ff @(posedge clk) begin
        if (reset) begin
            acc_reg <= '0;
            a_out   <= '0;
            b_out   <= '0;
        end else if (en) begin
            a_out <= a_in;
            b_out <= b_in;
            acc_reg <= acc_reg + {{(ACC_W-16){product[15]}}, product}; // sign-extend
        end
    end

    assign acc_out = acc_reg;

endmodule

tb/tb_pe.sv
// tb/tb_pe.sv
`timescale 1ns/1ps

module tb_pe;

    logic clk, reset, en;
    logic signed [7:0]  a_in, b_in;
    logic signed [7:0]  a_out, b_out;
    logic signed [31:0] acc_out;

    // DUT
    pe dut (
        .clk(clk),
        .reset(reset),
        .en(en),
        .a_in(a_in),
        .b_in(b_in),
        .a_out(a_out),
        .b_out(b_out),
        .acc_out(acc_out)
    );

    // 100MHz clock (10ns period)
    always #5 clk = ~clk;

    // Scoreboard
    logic signed [31:0] expected_acc;

    task drive(input logic signed [7:0] a, input logic signed [7:0] b);
        begin
            a_in = a;
            b_in = b;
        end
    endtask

    task step_and_check(input logic signed [7:0] a, input logic signed [7:0] b);
        begin
            drive(a, b);
            @(posedge clk); #1;

            expected_acc += (a * b);

            if (acc_out !== expected_acc)
                $fatal(1, "Mismatch: a=%0d b=%0d acc=%0d exp=%0d", a, b, acc_out, expected_acc);
        end
    endtask

    initial begin
        $dumpfile("sim/pe.vcd");
        $dumpvars(0, tb_pe);

        clk = 0;
        reset = 1;
        en = 0;
        a_in = 0;
        b_in = 0;
        expected_acc = 0;

        repeat (3) @(posedge clk);
        reset = 0;

        @(posedge clk);
        en = 1;

        // Test vectors (include negatives)
        step_and_check( 8'sd3,   8'sd4);     // +12
        step_and_check(-8'sd2,   8'sd7);     // -14
        step_and_check( 8'sd10, -8'sd10);    // -100
        step_and_check(-8'sd8,  -8'sd8);     // +64

        // Hold-state test
        en = 0;
        drive(8'sd100, 8'sd2);
        @(posedge clk); #1;
        if (acc_out !== expected_acc)
            $fatal(1, "Mismatch when en=0: acc=%0d exp=%0d", acc_out, expected_acc);

        $display("PASS: PE basic MAC + signed behavior verified.");
        $finish;
    end

endmodule

sim/pe.vcd
$date
	Mon Jan  5 01:43:12 2026
$end
$version
	Icarus Verilog
$end
$timescale
	1ps
$end
$scope module tb_pe $end
$var wire 8 ! b_out [7:0] $end
$var wire 32 " acc_out [31:0] $end
$var wire 8 # a_out [7:0] $end
$var reg 8 $ a_in [7:0] $end
$var reg 8 % b_in [7:0] $end
$var reg 1 & clk $end
$var reg 1 ' en $end
$var reg 32 ( expected_acc [31:0] $end
$var reg 1 ) reset $end
$scope module dut $end
$var wire 8 * a_in [7:0] $end
$var wire 32 + acc_out [31:0] $end
$var wire 8 , b_in [7:0] $end
$var wire 1 & clk $end
$var wire 1 ' en $end
$var wire 1 ) reset $end
$var wire 16 - product [15:0] $end
$var parameter 32 . ACC_W $end
$var reg 8 / a_out [7:0] $end
$var reg 32 0 acc_reg [31:0] $end
$var reg 8 1 b_out [7:0] $end
$upscope $end
$scope task drive $end
$var reg 8 2 a [7:0] $end
$var reg 8 3 b [7:0] $end
$upscope $end
$scope task step_and_check $end
$var reg 8 4 a [7:0] $end
$var reg 8 5 b [7:0] $end
$upscope $end
$upscope $end
$enddefinitions $end
$comment Show the parameter values. $end
$dumpall
b100000 .
$end
#0
$dumpvars
bx 5
bx 4
bx 3
bx 2
bx 1
bx 0
bx /
b0 -
b0 ,
bx +
b0 *
1)
b0 (
0'
0&
b0 %
b0 $
bx #
bx "
bx !
$end
#5000
b0 !
b0 1
b0 #
b0 /
b0 "
b0 +
b0 0
1&
#10000
0&
#15000
1&
#20000
0&
#25000
0)
1&
#30000
0&
#35000
b1100 -
b100 %
b100 ,
b11 $
b11 *
b100 3
b11 2
b100 5
b11 4
1'
1&
#40000
0&
#45000
b1100 "
b1100 +
b1100 0
b100 !
b100 1
b11 #
b11 /
1&
#46000
b111 %
b111 ,
b1111111111110010 -
b11111110 $
b11111110 *
b111 3
b11111110 2
b111 5
b11111110 4
b1100 (
#50000
0&
#55000
b11111111111111111111111111111110 "
b11111111111111111111111111111110 +
b11111111111111111111111111111110 0
b111 !
b111 1
b11111110 #
b11111110 /
1&
#56000
b11110110 %
b11110110 ,
b1111111110011100 -
b1010 $
b1010 *
b11110110 3
b1010 2
b11110110 5
b1010 4
b11111111111111111111111111111110 (
#60000
0&
#65000
b11111111111111111111111110011010 "
b11111111111111111111111110011010 +
b11111111111111111111111110011010 0
b11110110 !
b11110110 1
b1010 #
b1010 /
1&
#66000
b11111000 %
b11111000 ,
b1000000 -
b11111000 $
b11111000 *
b11111000 3
b11111000 2
b11111000 5
b11111000 4
b11111111111111111111111110011010 (
#70000
0&
#75000
b11111111111111111111111111011010 "
b11111111111111111111111111011010 +
b11111111111111111111111111011010 0
b11111000 !
b11111000 1
b11111000 #
b11111000 /
1&
#76000
b10 %
b10 ,
b11001000 -
b1100100 $
b1100100 *
b10 3
b1100100 2
0'
b11111111111111111111111111011010 (
