rtl/pe.sv
// rtl/pe.sv
module pe #(
    parameter int ACC_W = 32
) (
    input  logic                 clk,
    input  logic                 reset,   
    input  logic                 en,     

    input  logic signed [7:0]     a_in,
    input  logic signed [7:0]     b_in,

    output logic signed [7:0]     a_out,
    output logic signed [7:0]     b_out,

    output logic signed [ACC_W-1:0] acc_out
);

    // Internal register
    logic signed [ACC_W-1:0] acc_reg;

    // Compute product as signed 16-bit
    logic signed [15:0] product;
    assign product = a_in * b_in; 

    always_ff @(posedge clk) begin
        if (reset) begin
            acc_reg <= '0;
            a_out   <= '0;
            b_out   <= '0;
        end else if (en) begin
            a_out <= a_in;
            b_out <= b_in;
            acc_reg <= acc_reg + {{(ACC_W-16){product[15]}}, product}; // sign-extend
        end
    end

    assign acc_out = acc_reg;

endmodule

rtl/sa2x2.sv
// rtl/sa2x2.sv
module sa2x2 (
    input  logic clk,
    input  logic reset,
    input  logic en,

    // A from the left 
    input  logic signed [7:0] a_row0_in,
    input  logic signed [7:0] a_row1_in,

    // B from the top
    input  logic signed [7:0] b_col0_in,
    input  logic signed [7:0] b_col1_in,

    // Outputs
    output logic signed [31:0] c00,
    output logic signed [31:0] c01,
    output logic signed [31:0] c10,
    output logic signed [31:0] c11
);

    // Interconnect wires
    logic signed [7:0] a00_to_a01, a10_to_a11;
    logic signed [7:0] b00_to_b10, b01_to_b11;

    // PE(0,0)
    pe pe00 (
        .clk(clk), .reset(reset), .en(en),
        .a_in(a_row0_in),
        .b_in(b_col0_in),
        .a_out(a00_to_a01),
        .b_out(b00_to_b10),
        .acc_out(c00)
    );

    // PE(0,1)
    pe pe01 (
        .clk(clk), .reset(reset), .en(en),
        .a_in(a00_to_a01),
        .b_in(b_col1_in),
        .a_out(),              
        .b_out(b01_to_b11),
        .acc_out(c01)
    );

    // PE(1,0)
    pe pe10 (
        .clk(clk), .reset(reset), .en(en),
        .a_in(a_row1_in),
        .b_in(b00_to_b10),
        .a_out(a10_to_a11),
        .b_out(),            
        .acc_out(c10)
    );

    // PE(1,1)
    pe pe11 (
        .clk(clk), .reset(reset), .en(en),
        .a_in(a10_to_a11),
        .b_in(b01_to_b11),
        .a_out(), .b_out(),
        .acc_out(c11)
    );

endmodule

tb/tb_sa2x2.sv
// tb/tb_sa2x2.sv
`timescale 1ns/1ps

module tb_sa2x2;

    logic clk, reset, en;

    logic signed [7:0] a_row0_in, a_row1_in;
    logic signed [7:0] b_col0_in, b_col1_in;

    logic signed [31:0] c00, c01, c10, c11;

    sa2x2 dut (
        .clk(clk), .reset(reset), .en(en),
        .a_row0_in(a_row0_in), .a_row1_in(a_row1_in),
        .b_col0_in(b_col0_in), .b_col1_in(b_col1_in),
        .c00(c00), .c01(c01), .c10(c10), .c11(c11)
    );

    always #5 clk = ~clk; 

    task inject(
        input logic signed [7:0] a0,
        input logic signed [7:0] a1,
        input logic signed [7:0] b0,
        input logic signed [7:0] b1
    );
        begin
            a_row0_in = a0;
            a_row1_in = a1;
            b_col0_in = b0;
            b_col1_in = b1;
            @(posedge clk); #1;
        end
    endtask

    initial begin
        $dumpfile("sim/sa2x2.vcd");
        $dumpvars(0, tb_sa2x2);

        clk = 0; reset = 1; en = 0;
        a_row0_in = 0; a_row1_in = 0;
        b_col0_in = 0; b_col1_in = 0;

        repeat (3) @(posedge clk);
        reset = 0;

        @(posedge clk);
        en = 1;

        // Matrices:
        // A = [[1,2],[3,4]]
        // B = [[5,6],[7,8]]
        // Expected:
        // C00=19, C01=22, C10=43, C11=50

        // t=0
        inject(8'sd1, 8'sd0, 8'sd5, 8'sd0);

        // t=1
        inject(8'sd2, 8'sd3, 8'sd7, 8'sd6);

        // t=2
        inject(8'sd0, 8'sd4, 8'sd0, 8'sd8);

        // Flush
        inject(0,0,0,0);
        inject(0,0,0,0);

        // Hold and check
        en = 0;
        @(posedge clk); #1;

        if (c00 !== 32'sd19) $fatal(1, "c00 mismatch: got %0d exp 19", c00);
        if (c01 !== 32'sd22) $fatal(1, "c01 mismatch: got %0d exp 22", c01);
        if (c10 !== 32'sd43) $fatal(1, "c10 mismatch: got %0d exp 43", c10);
        if (c11 !== 32'sd50) $fatal(1, "c11 mismatch: got %0d exp 50", c11);

        $display("PASS: 2x2 systolic array computes A*B correctly (aligned schedule).");
        $finish;
    end

endmodule

sim/sa2x2.vcd
$date
	Mon Jan  5 17:10:17 2026
$end
$version
	Icarus Verilog
$end
$timescale
	1ps
$end
$scope module tb_sa2x2 $end
$var wire 32 ! c11 [31:0] $end
$var wire 32 " c10 [31:0] $end
$var wire 32 # c01 [31:0] $end
$var wire 32 $ c00 [31:0] $end
$var reg 8 % a_row0_in [7:0] $end
$var reg 8 & a_row1_in [7:0] $end
$var reg 8 ' b_col0_in [7:0] $end
$var reg 8 ( b_col1_in [7:0] $end
$var reg 1 ) clk $end
$var reg 1 * en $end
$var reg 1 + reset $end
$scope module dut $end
$var wire 8 , a_row0_in [7:0] $end
$var wire 8 - a_row1_in [7:0] $end
$var wire 8 . b_col0_in [7:0] $end
$var wire 8 / b_col1_in [7:0] $end
$var wire 1 ) clk $end
$var wire 1 * en $end
$var wire 1 + reset $end
$var wire 32 0 c11 [31:0] $end
$var wire 32 1 c10 [31:0] $end
$var wire 32 2 c01 [31:0] $end
$var wire 32 3 c00 [31:0] $end
$var wire 8 4 b01_to_b11 [7:0] $end
$var wire 8 5 b00_to_b10 [7:0] $end
$var wire 8 6 a10_to_a11 [7:0] $end
$var wire 8 7 a00_to_a01 [7:0] $end
$scope module pe00 $end
$var wire 8 8 a_in [7:0] $end
$var wire 32 9 acc_out [31:0] $end
$var wire 8 : b_in [7:0] $end
$var wire 1 ) clk $end
$var wire 1 * en $end
$var wire 1 + reset $end
$var wire 16 ; product [15:0] $end
$var parameter 32 < ACC_W $end
$var reg 8 = a_out [7:0] $end
$var reg 32 > acc_reg [31:0] $end
$var reg 8 ? b_out [7:0] $end
$upscope $end
$scope module pe01 $end
$var wire 8 @ a_in [7:0] $end
$var wire 32 A acc_out [31:0] $end
$var wire 8 B b_in [7:0] $end
$var wire 1 ) clk $end
$var wire 1 * en $end
$var wire 1 + reset $end
$var wire 16 C product [15:0] $end
$var parameter 32 D ACC_W $end
$var reg 8 E a_out [7:0] $end
$var reg 32 F acc_reg [31:0] $end
$var reg 8 G b_out [7:0] $end
$upscope $end
$scope module pe10 $end
$var wire 8 H a_in [7:0] $end
$var wire 32 I acc_out [31:0] $end
$var wire 8 J b_in [7:0] $end
$var wire 1 ) clk $end
$var wire 1 * en $end
$var wire 1 + reset $end
$var wire 16 K product [15:0] $end
$var parameter 32 L ACC_W $end
$var reg 8 M a_out [7:0] $end
$var reg 32 N acc_reg [31:0] $end
$var reg 8 O b_out [7:0] $end
$upscope $end
$scope module pe11 $end
$var wire 8 P a_in [7:0] $end
$var wire 32 Q acc_out [31:0] $end
$var wire 8 R b_in [7:0] $end
$var wire 1 ) clk $end
$var wire 1 * en $end
$var wire 1 + reset $end
$var wire 16 S product [15:0] $end
$var parameter 32 T ACC_W $end
$var reg 8 U a_out [7:0] $end
$var reg 32 V acc_reg [31:0] $end
$var reg 8 W b_out [7:0] $end
$upscope $end
$upscope $end
$scope task inject $end
$var reg 8 X a0 [7:0] $end
$var reg 8 Y a1 [7:0] $end
$var reg 8 Z b0 [7:0] $end
$var reg 8 [ b1 [7:0] $end
$upscope $end
$upscope $end
$enddefinitions $end
$comment Show the parameter values. $end
$dumpall
b100000 T
b100000 L
b100000 D
b100000 <
$end
#0
$dumpvars
bx [
bx Z
bx Y
bx X
bx W
bx V
bx U
bx S
bx R
bx Q
bx P
bx O
bx N
bx M
bx K
bx J
bx I
b0 H
bx G
bx F
bx E
bx C
b0 B
bx A
bx @
bx ?
bx >
bx =
b0 ;
b0 :
bx 9
b0 8
bx 7
bx 6
bx 5
bx 4
bx 3
bx 2
bx 1
bx 0
b0 /
b0 .
b0 -
b0 ,
1+
0*
0)
b0 (
b0 '
b0 &
b0 %
bx $
bx #
bx "
bx !
$end
#5000
b0 K
b0 5
b0 ?
b0 J
b0 C
b0 7
b0 =
b0 @
b0 $
b0 3
b0 9
b0 >
b0 S
b0 4
b0 G
b0 R
b0 E
b0 #
b0 2
b0 A
b0 F
b0 O
b0 6
b0 M
b0 P
b0 "
b0 1
b0 I
b0 N
b0 W
b0 U
b0 !
b0 0
b0 Q
b0 V
1)
#10000
0)
#15000
1)
#20000
0)
#25000
0+
1)
#30000
0)
#35000
b101 ;
b101 '
b101 .
b101 :
b1 %
b1 ,
b1 8
b0 [
b101 Z
b0 Y
b1 X
1*
1)
#40000
0)
#45000
b101 $
b101 3
b101 9
b101 >
b101 5
b101 ?
b101 J
b1 7
b1 =
b1 @
1)
#46000
b110 C
b110 (
b110 /
b110 B
b111 '
b111 .
b111 :
b1111 K
b11 &
b11 -
b11 H
b1110 ;
b10 %
b10 ,
b10 8
b110 [
b111 Z
b11 Y
b10 X
#50000
0)
#55000
b1111 "
b1111 1
b1111 I
b1111 N
b101 O
b10010 S
b11 6
b11 M
b11 P
b110 #
b110 2
b110 A
b110 F
b110 4
b110 G
b110 R
b1 E
b10011 $
b10011 3
b10011 9
b10011 >
b10101 K
b111 5
b111 ?
b111 J
b1100 C
b10 7
b10 =
b10 @
1)
#56000
b10000 C
b1000 (
b1000 /
b1000 B
b0 '
b0 .
b0 :
b11100 K
b100 &
b100 -
b100 H
b0 ;
b0 %
b0 ,
b0 8
b1000 [
b0 Z
b100 Y
b0 X
#60000
0)
#65000
b0 K
b0 5
b0 ?
b0 J
b0 C
b0 7
b0 =
b0 @
b10110 #
b10110 2
b10110 A
b10110 F
b1000 4
b1000 G
b1000 R
b10 E
b101011 "
b101011 1
b101011 I
b101011 N
b111 O
b100000 S
b100 6
b100 M
b100 P
b10010 !
b10010 0
b10010 Q
b10010 V
b110 W
b11 U
1)
#66000
b0 (
b0 /
b0 B
b0 &
b0 -
b0 H
b0 [
b0 Y
#70000
0)
#75000
b110010 !
b110010 0
b110010 Q
b110010 V
b1000 W
b100 U
b0 O
b0 6
b0 M
b0 P
b0 S
b0 4
b0 G
b0 R
b0 E
1)
#80000
0)
#85000
b0 W
b0 U
1)
#86000
0*
