rtl/pe.sv
// rtl/pe.sv
module pe #(
    parameter int ACC_W = 32
) (
    input  logic                 clk,
    input  logic                 reset,   
    input  logic                 en,     

    input  logic signed [7:0]     a_in,
    input  logic signed [7:0]     b_in,

    output logic signed [7:0]     a_out,
    output logic signed [7:0]     b_out,

    output logic signed [ACC_W-1:0] acc_out
);

    // Internal register
    logic signed [ACC_W-1:0] acc_reg;

    // Compute product as signed 16-bit
    logic signed [15:0] product;
    assign product = a_in * b_in; 

    always_ff @(posedge clk) begin
        if (reset) begin
            acc_reg <= '0;
            a_out   <= '0;
            b_out   <= '0;
        end else if (en) begin
            a_out <= a_in;
            b_out <= b_in;
            acc_reg <= acc_reg + {{(ACC_W-16){product[15]}}, product}; // sign-extend
        end
    end

    assign acc_out = acc_reg;

endmodule

rtl/sa4x4.sv
// rtl/sa4x4.sv
module sa4x4 #(
    parameter int ACC_W = 32
)(
    input  logic clk,
    input  logic reset,
    input  logic en,

    input  logic signed [7:0] a0, a1, a2, a3,   
    input  logic signed [7:0] b0, b1, b2, b3,

    output logic signed [ACC_W-1:0] c00, c01, c02, c03,
    output logic signed [ACC_W-1:0] c10, c11, c12, c13,
    output logic signed [ACC_W-1:0] c20, c21, c22, c23,
    output logic signed [ACC_W-1:0] c30, c31, c32, c33
);

    // Internal interconnect 
    logic signed [7:0] a_to_pe [4][4];
    logic signed [7:0] b_to_pe [4][4];
    logic signed [7:0] a_fwd   [4][4];
    logic signed [7:0] b_fwd   [4][4];

    // Left edge A injections
    assign a_to_pe[0][0] = a0;  assign a_to_pe[1][0] = a1;
    assign a_to_pe[2][0] = a2;  assign a_to_pe[3][0] = a3;

    // Top edge B injections
    assign b_to_pe[0][0] = b0;  assign b_to_pe[0][1] = b1;
    assign b_to_pe[0][2] = b2;  assign b_to_pe[0][3] = b3;

    // Internal A propagation (right)
    assign a_to_pe[0][1] = a_fwd[0][0];
    assign a_to_pe[0][2] = a_fwd[0][1];
    assign a_to_pe[0][3] = a_fwd[0][2];

    assign a_to_pe[1][1] = a_fwd[1][0];
    assign a_to_pe[1][2] = a_fwd[1][1];
    assign a_to_pe[1][3] = a_fwd[1][2];

    assign a_to_pe[2][1] = a_fwd[2][0];
    assign a_to_pe[2][2] = a_fwd[2][1];
    assign a_to_pe[2][3] = a_fwd[2][2];

    assign a_to_pe[3][1] = a_fwd[3][0];
    assign a_to_pe[3][2] = a_fwd[3][1];
    assign a_to_pe[3][3] = a_fwd[3][2];

    // Internal B propagation (down)
    assign b_to_pe[1][0] = b_fwd[0][0];
    assign b_to_pe[2][0] = b_fwd[1][0];
    assign b_to_pe[3][0] = b_fwd[2][0];

    assign b_to_pe[1][1] = b_fwd[0][1];
    assign b_to_pe[2][1] = b_fwd[1][1];
    assign b_to_pe[3][1] = b_fwd[2][1];

    assign b_to_pe[1][2] = b_fwd[0][2];
    assign b_to_pe[2][2] = b_fwd[1][2];
    assign b_to_pe[3][2] = b_fwd[2][2];

    assign b_to_pe[1][3] = b_fwd[0][3];
    assign b_to_pe[2][3] = b_fwd[1][3];
    assign b_to_pe[3][3] = b_fwd[2][3];

    // 16 PE instances
    pe #(.ACC_W(ACC_W)) pe00(.clk(clk),.reset(reset),.en(en),.a_in(a_to_pe[0][0]),.b_in(b_to_pe[0][0]),.a_out(a_fwd[0][0]),.b_out(b_fwd[0][0]),.acc_out(c00));
    pe #(.ACC_W(ACC_W)) pe01(.clk(clk),.reset(reset),.en(en),.a_in(a_to_pe[0][1]),.b_in(b_to_pe[0][1]),.a_out(a_fwd[0][1]),.b_out(b_fwd[0][1]),.acc_out(c01));
    pe #(.ACC_W(ACC_W)) pe02(.clk(clk),.reset(reset),.en(en),.a_in(a_to_pe[0][2]),.b_in(b_to_pe[0][2]),.a_out(a_fwd[0][2]),.b_out(b_fwd[0][2]),.acc_out(c02));
    pe #(.ACC_W(ACC_W)) pe03(.clk(clk),.reset(reset),.en(en),.a_in(a_to_pe[0][3]),.b_in(b_to_pe[0][3]),.a_out(a_fwd[0][3]),.b_out(b_fwd[0][3]),.acc_out(c03));

    pe #(.ACC_W(ACC_W)) pe10(.clk(clk),.reset(reset),.en(en),.a_in(a_to_pe[1][0]),.b_in(b_to_pe[1][0]),.a_out(a_fwd[1][0]),.b_out(b_fwd[1][0]),.acc_out(c10));
    pe #(.ACC_W(ACC_W)) pe11(.clk(clk),.reset(reset),.en(en),.a_in(a_to_pe[1][1]),.b_in(b_to_pe[1][1]),.a_out(a_fwd[1][1]),.b_out(b_fwd[1][1]),.acc_out(c11));
    pe #(.ACC_W(ACC_W)) pe12(.clk(clk),.reset(reset),.en(en),.a_in(a_to_pe[1][2]),.b_in(b_to_pe[1][2]),.a_out(a_fwd[1][2]),.b_out(b_fwd[1][2]),.acc_out(c12));
    pe #(.ACC_W(ACC_W)) pe13(.clk(clk),.reset(reset),.en(en),.a_in(a_to_pe[1][3]),.b_in(b_to_pe[1][3]),.a_out(a_fwd[1][3]),.b_out(b_fwd[1][3]),.acc_out(c13));

    pe #(.ACC_W(ACC_W)) pe20(.clk(clk),.reset(reset),.en(en),.a_in(a_to_pe[2][0]),.b_in(b_to_pe[2][0]),.a_out(a_fwd[2][0]),.b_out(b_fwd[2][0]),.acc_out(c20));
    pe #(.ACC_W(ACC_W)) pe21(.clk(clk),.reset(reset),.en(en),.a_in(a_to_pe[2][1]),.b_in(b_to_pe[2][1]),.a_out(a_fwd[2][1]),.b_out(b_fwd[2][1]),.acc_out(c21));
    pe #(.ACC_W(ACC_W)) pe22(.clk(clk),.reset(reset),.en(en),.a_in(a_to_pe[2][2]),.b_in(b_to_pe[2][2]),.a_out(a_fwd[2][2]),.b_out(b_fwd[2][2]),.acc_out(c22));
    pe #(.ACC_W(ACC_W)) pe23(.clk(clk),.reset(reset),.en(en),.a_in(a_to_pe[2][3]),.b_in(b_to_pe[2][3]),.a_out(a_fwd[2][3]),.b_out(b_fwd[2][3]),.acc_out(c23));

    pe #(.ACC_W(ACC_W)) pe30(.clk(clk),.reset(reset),.en(en),.a_in(a_to_pe[3][0]),.b_in(b_to_pe[3][0]),.a_out(a_fwd[3][0]),.b_out(b_fwd[3][0]),.acc_out(c30));
    pe #(.ACC_W(ACC_W)) pe31(.clk(clk),.reset(reset),.en(en),.a_in(a_to_pe[3][1]),.b_in(b_to_pe[3][1]),.a_out(a_fwd[3][1]),.b_out(b_fwd[3][1]),.acc_out(c31));
    pe #(.ACC_W(ACC_W)) pe32(.clk(clk),.reset(reset),.en(en),.a_in(a_to_pe[3][2]),.b_in(b_to_pe[3][2]),.a_out(a_fwd[3][2]),.b_out(b_fwd[3][2]),.acc_out(c32));
    pe #(.ACC_W(ACC_W)) pe33(.clk(clk),.reset(reset),.en(en),.a_in(a_to_pe[3][3]),.b_in(b_to_pe[3][3]),.a_out(a_fwd[3][3]),.b_out(b_fwd[3][3]),.acc_out(c33));

endmodule

tb/tb_sa4x4_flat.sv
// tb/tb_sa4x4_flat.sv
`timescale 1ns/1ps

module tb_sa4x4_flat;

    localparam int N = 4;
    localparam int ACC_W = 32;

    logic clk, reset, en;

    // Flattened inputs
    logic signed [7:0] a0, a1, a2, a3;
    logic signed [7:0] b0, b1, b2, b3;

    // Flattened outputs
    logic signed [ACC_W-1:0] c00, c01, c02, c03;
    logic signed [ACC_W-1:0] c10, c11, c12, c13;
    logic signed [ACC_W-1:0] c20, c21, c22, c23;
    logic signed [ACC_W-1:0] c30, c31, c32, c33;

    // DUT
    sa4x4 #(.ACC_W(ACC_W)) dut (
        .clk(clk), .reset(reset), .en(en),
        .a0(a0), .a1(a1), .a2(a2), .a3(a3),
        .b0(b0), .b1(b1), .b2(b2), .b3(b3),
        .c00(c00), .c01(c01), .c02(c02), .c03(c03),
        .c10(c10), .c11(c11), .c12(c12), .c13(c13),
        .c20(c20), .c21(c21), .c22(c22), .c23(c23),
        .c30(c30), .c31(c31), .c32(c32), .c33(c33)
    );

    always #5 clk = ~clk;

    // Reference matrices
    logic signed [7:0] A [N][N];
    logic signed [7:0] B [N][N];
    logic signed [ACC_W-1:0] C_ref [N][N];

    integer i, j, k;

    task compute_reference;
        begin
            for (i = 0; i < N; i++) begin
                for (j = 0; j < N; j++) begin
                    C_ref[i][j] = '0;
                    for (k = 0; k < N; k++) begin
                        C_ref[i][j] += A[i][k] * B[k][j];
                    end
                end
            end
        end
    endtask

    // Inject one systolic time step t using skew rule
    task inject_time(input int t);
        int kk;
        begin
            // Row 0
            kk = t - 0; a0 = (kk>=0 && kk<N) ? A[0][kk] : 0;
            kk = t - 1; a1 = (kk>=0 && kk<N) ? A[1][kk] : 0;
            kk = t - 2; a2 = (kk>=0 && kk<N) ? A[2][kk] : 0;
            kk = t - 3; a3 = (kk>=0 && kk<N) ? A[3][kk] : 0;

            // Col 0
            kk = t - 0; b0 = (kk>=0 && kk<N) ? B[kk][0] : 0;
            kk = t - 1; b1 = (kk>=0 && kk<N) ? B[kk][1] : 0;
            kk = t - 2; b2 = (kk>=0 && kk<N) ? B[kk][2] : 0;
            kk = t - 3; b3 = (kk>=0 && kk<N) ? B[kk][3] : 0;

            @(posedge clk); #1;
        end
    endtask

    task check_outputs;
        begin
            if (c00 !== C_ref[0][0]) $fatal(1,"Mismatch C[0][0]: got %0d exp %0d", c00, C_ref[0][0]);
            if (c01 !== C_ref[0][1]) $fatal(1,"Mismatch C[0][1]: got %0d exp %0d", c01, C_ref[0][1]);
            if (c02 !== C_ref[0][2]) $fatal(1,"Mismatch C[0][2]: got %0d exp %0d", c02, C_ref[0][2]);
            if (c03 !== C_ref[0][3]) $fatal(1,"Mismatch C[0][3]: got %0d exp %0d", c03, C_ref[0][3]);

            if (c10 !== C_ref[1][0]) $fatal(1,"Mismatch C[1][0]: got %0d exp %0d", c10, C_ref[1][0]);
            if (c11 !== C_ref[1][1]) $fatal(1,"Mismatch C[1][1]: got %0d exp %0d", c11, C_ref[1][1]);
            if (c12 !== C_ref[1][2]) $fatal(1,"Mismatch C[1][2]: got %0d exp %0d", c12, C_ref[1][2]);
            if (c13 !== C_ref[1][3]) $fatal(1,"Mismatch C[1][3]: got %0d exp %0d", c13, C_ref[1][3]);

            if (c20 !== C_ref[2][0]) $fatal(1,"Mismatch C[2][0]: got %0d exp %0d", c20, C_ref[2][0]);
            if (c21 !== C_ref[2][1]) $fatal(1,"Mismatch C[2][1]: got %0d exp %0d", c21, C_ref[2][1]);
            if (c22 !== C_ref[2][2]) $fatal(1,"Mismatch C[2][2]: got %0d exp %0d", c22, C_ref[2][2]);
            if (c23 !== C_ref[2][3]) $fatal(1,"Mismatch C[2][3]: got %0d exp %0d", c23, C_ref[2][3]);

            if (c30 !== C_ref[3][0]) $fatal(1,"Mismatch C[3][0]: got %0d exp %0d", c30, C_ref[3][0]);
            if (c31 !== C_ref[3][1]) $fatal(1,"Mismatch C[3][1]: got %0d exp %0d", c31, C_ref[3][1]);
            if (c32 !== C_ref[3][2]) $fatal(1,"Mismatch C[3][2]: got %0d exp %0d", c32, C_ref[3][2]);
            if (c33 !== C_ref[3][3]) $fatal(1,"Mismatch C[3][3]: got %0d exp %0d", c33, C_ref[3][3]);
        end
    endtask

    initial begin
        $dumpfile("sim/sa4x4.vcd");
        $dumpvars(0, tb_sa4x4_flat);

        clk = 0; reset = 1; en = 0;
        a0=0; a1=0; a2=0; a3=0;
        b0=0; b1=0; b2=0; b3=0;

        // Deterministic A and identity B
        for (i = 0; i < N; i++) begin
            for (j = 0; j < N; j++) begin
                A[i][j] = 8'(i*N + j + 1);
                B[i][j] = (i == j) ? 8'sd1 : 8'sd0;
            end
        end

        compute_reference();

        repeat (3) @(posedge clk);
        reset = 0;

        @(posedge clk);
        en = 1;

        for (int t = 0; t < 12; t++) begin
            inject_time(t);
        end

        repeat (2) @(posedge clk);
        en = 0;
        @(posedge clk); #1;

        check_outputs();
        $display("PASS: 4x4 systolic array matches reference GEMM (flattened wrapper).");
        $finish;
    end

endmodule

sim/sa4x4.vcd
$date
	Mon Jan  5 23:30:59 2026
$end
$version
	Icarus Verilog
$end
$timescale
	1ps
$end
$scope module tb_sa4x4_flat $end
$var wire 32 ! c33 [31:0] $end
$var wire 32 " c32 [31:0] $end
$var wire 32 # c31 [31:0] $end
$var wire 32 $ c30 [31:0] $end
$var wire 32 % c23 [31:0] $end
$var wire 32 & c22 [31:0] $end
$var wire 32 ' c21 [31:0] $end
$var wire 32 ( c20 [31:0] $end
$var wire 32 ) c13 [31:0] $end
$var wire 32 * c12 [31:0] $end
$var wire 32 + c11 [31:0] $end
$var wire 32 , c10 [31:0] $end
$var wire 32 - c03 [31:0] $end
$var wire 32 . c02 [31:0] $end
$var wire 32 / c01 [31:0] $end
$var wire 32 0 c00 [31:0] $end
$var parameter 32 1 ACC_W $end
$var parameter 32 2 N $end
$var reg 8 3 a0 [7:0] $end
$var reg 8 4 a1 [7:0] $end
$var reg 8 5 a2 [7:0] $end
$var reg 8 6 a3 [7:0] $end
$var reg 8 7 b0 [7:0] $end
$var reg 8 8 b1 [7:0] $end
$var reg 8 9 b2 [7:0] $end
$var reg 8 : b3 [7:0] $end
$var reg 1 ; clk $end
$var reg 1 < en $end
$var reg 1 = reset $end
$var integer 32 > i [31:0] $end
$var integer 32 ? j [31:0] $end
$var integer 32 @ k [31:0] $end
$scope module dut $end
$var wire 8 A a0 [7:0] $end
$var wire 8 B a1 [7:0] $end
$var wire 8 C a2 [7:0] $end
$var wire 8 D a3 [7:0] $end
$var wire 8 E b0 [7:0] $end
$var wire 8 F b1 [7:0] $end
$var wire 8 G b2 [7:0] $end
$var wire 8 H b3 [7:0] $end
$var wire 1 ; clk $end
$var wire 1 < en $end
$var wire 1 = reset $end
$var wire 32 I c33 [31:0] $end
$var wire 32 J c32 [31:0] $end
$var wire 32 K c31 [31:0] $end
$var wire 32 L c30 [31:0] $end
$var wire 32 M c23 [31:0] $end
$var wire 32 N c22 [31:0] $end
$var wire 32 O c21 [31:0] $end
$var wire 32 P c20 [31:0] $end
$var wire 32 Q c13 [31:0] $end
$var wire 32 R c12 [31:0] $end
$var wire 32 S c11 [31:0] $end
$var wire 32 T c10 [31:0] $end
$var wire 32 U c03 [31:0] $end
$var wire 32 V c02 [31:0] $end
$var wire 32 W c01 [31:0] $end
$var wire 32 X c00 [31:0] $end
$var parameter 32 Y ACC_W $end
$scope module pe00 $end
$var wire 8 Z a_in [7:0] $end
$var wire 32 [ acc_out [31:0] $end
$var wire 8 \ b_in [7:0] $end
$var wire 1 ; clk $end
$var wire 1 < en $end
$var wire 1 = reset $end
$var wire 16 ] product [15:0] $end
$var parameter 32 ^ ACC_W $end
$var reg 8 _ a_out [7:0] $end
$var reg 32 ` acc_reg [31:0] $end
$var reg 8 a b_out [7:0] $end
$upscope $end
$scope module pe01 $end
$var wire 8 b a_in [7:0] $end
$var wire 32 c acc_out [31:0] $end
$var wire 8 d b_in [7:0] $end
$var wire 1 ; clk $end
$var wire 1 < en $end
$var wire 1 = reset $end
$var wire 16 e product [15:0] $end
$var parameter 32 f ACC_W $end
$var reg 8 g a_out [7:0] $end
$var reg 32 h acc_reg [31:0] $end
$var reg 8 i b_out [7:0] $end
$upscope $end
$scope module pe02 $end
$var wire 8 j a_in [7:0] $end
$var wire 32 k acc_out [31:0] $end
$var wire 8 l b_in [7:0] $end
$var wire 1 ; clk $end
$var wire 1 < en $end
$var wire 1 = reset $end
$var wire 16 m product [15:0] $end
$var parameter 32 n ACC_W $end
$var reg 8 o a_out [7:0] $end
$var reg 32 p acc_reg [31:0] $end
$var reg 8 q b_out [7:0] $end
$upscope $end
$scope module pe03 $end
$var wire 8 r a_in [7:0] $end
$var wire 32 s acc_out [31:0] $end
$var wire 8 t b_in [7:0] $end
$var wire 1 ; clk $end
$var wire 1 < en $end
$var wire 1 = reset $end
$var wire 16 u product [15:0] $end
$var parameter 32 v ACC_W $end
$var reg 8 w a_out [7:0] $end
$var reg 32 x acc_reg [31:0] $end
$var reg 8 y b_out [7:0] $end
$upscope $end
$scope module pe10 $end
$var wire 8 z a_in [7:0] $end
$var wire 32 { acc_out [31:0] $end
$var wire 8 | b_in [7:0] $end
$var wire 1 ; clk $end
$var wire 1 < en $end
$var wire 1 = reset $end
$var wire 16 } product [15:0] $end
$var parameter 32 ~ ACC_W $end
$var reg 8 !" a_out [7:0] $end
$var reg 32 "" acc_reg [31:0] $end
$var reg 8 #" b_out [7:0] $end
$upscope $end
$scope module pe11 $end
$var wire 8 $" a_in [7:0] $end
$var wire 32 %" acc_out [31:0] $end
$var wire 8 &" b_in [7:0] $end
$var wire 1 ; clk $end
$var wire 1 < en $end
$var wire 1 = reset $end
$var wire 16 '" product [15:0] $end
$var parameter 32 (" ACC_W $end
$var reg 8 )" a_out [7:0] $end
$var reg 32 *" acc_reg [31:0] $end
$var reg 8 +" b_out [7:0] $end
$upscope $end
$scope module pe12 $end
$var wire 8 ," a_in [7:0] $end
$var wire 32 -" acc_out [31:0] $end
$var wire 8 ." b_in [7:0] $end
$var wire 1 ; clk $end
$var wire 1 < en $end
$var wire 1 = reset $end
$var wire 16 /" product [15:0] $end
$var parameter 32 0" ACC_W $end
$var reg 8 1" a_out [7:0] $end
$var reg 32 2" acc_reg [31:0] $end
$var reg 8 3" b_out [7:0] $end
$upscope $end
$scope module pe13 $end
$var wire 8 4" a_in [7:0] $end
$var wire 32 5" acc_out [31:0] $end
$var wire 8 6" b_in [7:0] $end
$var wire 1 ; clk $end
$var wire 1 < en $end
$var wire 1 = reset $end
$var wire 16 7" product [15:0] $end
$var parameter 32 8" ACC_W $end
$var reg 8 9" a_out [7:0] $end
$var reg 32 :" acc_reg [31:0] $end
$var reg 8 ;" b_out [7:0] $end
$upscope $end
$scope module pe20 $end
$var wire 8 <" a_in [7:0] $end
$var wire 32 =" acc_out [31:0] $end
$var wire 8 >" b_in [7:0] $end
$var wire 1 ; clk $end
$var wire 1 < en $end
$var wire 1 = reset $end
$var wire 16 ?" product [15:0] $end
$var parameter 32 @" ACC_W $end
$var reg 8 A" a_out [7:0] $end
$var reg 32 B" acc_reg [31:0] $end
$var reg 8 C" b_out [7:0] $end
$upscope $end
$scope module pe21 $end
$var wire 8 D" a_in [7:0] $end
$var wire 32 E" acc_out [31:0] $end
$var wire 8 F" b_in [7:0] $end
$var wire 1 ; clk $end
$var wire 1 < en $end
$var wire 1 = reset $end
$var wire 16 G" product [15:0] $end
$var parameter 32 H" ACC_W $end
$var reg 8 I" a_out [7:0] $end
$var reg 32 J" acc_reg [31:0] $end
$var reg 8 K" b_out [7:0] $end
$upscope $end
$scope module pe22 $end
$var wire 8 L" a_in [7:0] $end
$var wire 32 M" acc_out [31:0] $end
$var wire 8 N" b_in [7:0] $end
$var wire 1 ; clk $end
$var wire 1 < en $end
$var wire 1 = reset $end
$var wire 16 O" product [15:0] $end
$var parameter 32 P" ACC_W $end
$var reg 8 Q" a_out [7:0] $end
$var reg 32 R" acc_reg [31:0] $end
$var reg 8 S" b_out [7:0] $end
$upscope $end
$scope module pe23 $end
$var wire 8 T" a_in [7:0] $end
$var wire 32 U" acc_out [31:0] $end
$var wire 8 V" b_in [7:0] $end
$var wire 1 ; clk $end
$var wire 1 < en $end
$var wire 1 = reset $end
$var wire 16 W" product [15:0] $end
$var parameter 32 X" ACC_W $end
$var reg 8 Y" a_out [7:0] $end
$var reg 32 Z" acc_reg [31:0] $end
$var reg 8 [" b_out [7:0] $end
$upscope $end
$scope module pe30 $end
$var wire 8 \" a_in [7:0] $end
$var wire 32 ]" acc_out [31:0] $end
$var wire 8 ^" b_in [7:0] $end
$var wire 1 ; clk $end
$var wire 1 < en $end
$var wire 1 = reset $end
$var wire 16 _" product [15:0] $end
$var parameter 32 `" ACC_W $end
$var reg 8 a" a_out [7:0] $end
$var reg 32 b" acc_reg [31:0] $end
$var reg 8 c" b_out [7:0] $end
$upscope $end
$scope module pe31 $end
$var wire 8 d" a_in [7:0] $end
$var wire 32 e" acc_out [31:0] $end
$var wire 8 f" b_in [7:0] $end
$var wire 1 ; clk $end
$var wire 1 < en $end
$var wire 1 = reset $end
$var wire 16 g" product [15:0] $end
$var parameter 32 h" ACC_W $end
$var reg 8 i" a_out [7:0] $end
$var reg 32 j" acc_reg [31:0] $end
$var reg 8 k" b_out [7:0] $end
$upscope $end
$scope module pe32 $end
$var wire 8 l" a_in [7:0] $end
$var wire 32 m" acc_out [31:0] $end
$var wire 8 n" b_in [7:0] $end
$var wire 1 ; clk $end
$var wire 1 < en $end
$var wire 1 = reset $end
$var wire 16 o" product [15:0] $end
$var parameter 32 p" ACC_W $end
$var reg 8 q" a_out [7:0] $end
$var reg 32 r" acc_reg [31:0] $end
$var reg 8 s" b_out [7:0] $end
$upscope $end
$scope module pe33 $end
$var wire 8 t" a_in [7:0] $end
$var wire 32 u" acc_out [31:0] $end
$var wire 8 v" b_in [7:0] $end
$var wire 1 ; clk $end
$var wire 1 < en $end
$var wire 1 = reset $end
$var wire 16 w" product [15:0] $end
$var parameter 32 x" ACC_W $end
$var reg 8 y" a_out [7:0] $end
$var reg 32 z" acc_reg [31:0] $end
$var reg 8 {" b_out [7:0] $end
$upscope $end
$upscope $end
$scope begin $ivl_for_loop0 $end
$var integer 32 |" t [31:0] $end
$upscope $end
$scope task check_outputs $end
$upscope $end
$scope task compute_reference $end
$upscope $end
$scope task inject_time $end
$var integer 32 }" kk [31:0] $end
$var integer 32 ~" t [31:0] $end
$upscope $end
$upscope $end
$enddefinitions $end
$comment Show the parameter values. $end
$dumpall
b100000 x"
b100000 p"
b100000 h"
b100000 `"
b100000 X"
b100000 P"
b100000 H"
b100000 @"
b100000 8"
b100000 0"
b100000 ("
b100000 ~
b100000 v
b100000 n
b100000 f
b100000 ^
b100000 Y
b100 2
b100000 1
$end
#0
$dumpvars
b0 ~"
b0 }"
b0 |"
bx {"
bx z"
bx y"
bx w"
bx v"
bx u"
bx t"
bx s"
bx r"
bx q"
bx o"
bx n"
bx m"
bx l"
bx k"
bx j"
bx i"
bx g"
bx f"
bx e"
bx d"
bx c"
bx b"
bx a"
bx _"
bx ^"
bx ]"
b0 \"
bx ["
bx Z"
bx Y"
bx W"
bx V"
bx U"
bx T"
bx S"
bx R"
bx Q"
bx O"
bx N"
bx M"
bx L"
bx K"
bx J"
bx I"
bx G"
bx F"
bx E"
bx D"
bx C"
bx B"
bx A"
bx ?"
bx >"
bx ="
b0 <"
bx ;"
bx :"
bx 9"
bx 7"
bx 6"
bx 5"
bx 4"
bx 3"
bx 2"
bx 1"
bx /"
bx ."
bx -"
bx ,"
bx +"
bx *"
bx )"
bx '"
bx &"
bx %"
bx $"
bx #"
bx ""
bx !"
bx }
bx |
bx {
b0 z
bx y
bx x
bx w
bx u
b0 t
bx s
bx r
bx q
bx p
bx o
bx m
b0 l
bx k
bx j
bx i
bx h
bx g
bx e
b0 d
bx c
bx b
bx a
bx `
bx _
b0 ]
b0 \
bx [
b0 Z
bx X
bx W
bx V
bx U
bx T
bx S
bx R
bx Q
bx P
bx O
bx N
bx M
bx L
bx K
bx J
bx I
b0 H
b0 G
b0 F
b0 E
b0 D
b0 C
b0 B
b0 A
b100 @
b100 ?
b100 >
1=
0<
0;
b0 :
b0 9
b0 8
b0 7
b0 6
b0 5
b0 4
b0 3
bx 0
bx /
bx .
bx -
bx ,
bx +
bx *
bx )
bx (
bx '
bx &
bx %
bx $
bx #
bx "
bx !
$end
#5000
b0 }
b0 |
b0 a
b0 e
b0 b
b0 _
b0 0
b0 X
b0 [
b0 `
b0 '"
b0 &"
b0 i
b0 m
b0 j
b0 g
b0 /
b0 W
b0 c
b0 h
b0 /"
b0 ."
b0 q
b0 u
b0 r
b0 o
b0 .
b0 V
b0 k
b0 p
b0 7"
b0 6"
b0 y
b0 w
b0 -
b0 U
b0 s
b0 x
b0 ?"
b0 >"
b0 #"
b0 $"
b0 !"
b0 ,
b0 T
b0 {
b0 ""
b0 G"
b0 F"
b0 +"
b0 ,"
b0 )"
b0 +
b0 S
b0 %"
b0 *"
b0 O"
b0 N"
b0 3"
b0 4"
b0 1"
b0 *
b0 R
b0 -"
b0 2"
b0 W"
b0 V"
b0 ;"
b0 9"
b0 )
b0 Q
b0 5"
b0 :"
b0 _"
b0 ^"
b0 C"
b0 D"
b0 A"
b0 (
b0 P
b0 ="
b0 B"
b0 g"
b0 f"
b0 K"
b0 L"
b0 I"
b0 '
b0 O
b0 E"
b0 J"
b0 o"
b0 n"
b0 S"
b0 T"
b0 Q"
b0 &
b0 N
b0 M"
b0 R"
b0 w"
b0 v"
b0 ["
b0 Y"
b0 %
b0 M
b0 U"
b0 Z"
b0 c"
b0 d"
b0 a"
b0 $
b0 L
b0 ]"
b0 b"
b0 k"
b0 l"
b0 i"
b0 #
b0 K
b0 e"
b0 j"
b0 s"
b0 t"
b0 q"
b0 "
b0 J
b0 m"
b0 r"
b0 {"
b0 y"
b0 !
b0 I
b0 u"
b0 z"
1;
#10000
0;
#15000
1;
#20000
0;
#25000
0=
1;
#30000
0;
#35000
b1 ]
b1 \
b1 7
b1 E
b11111111111111111111111111111101 }"
b1 Z
b1 3
b1 A
1<
1;
#40000
0;
#45000
b1 0
b1 X
b1 [
b1 `
b1 |
b1 a
b1 b
b1 _
1;
#46000
b0 \
b0 7
b0 E
b101 }
b101 z
b101 4
b101 B
b0 ]
b10 Z
b10 3
b10 A
b11111111111111111111111111111110 }"
b1 ~"
b1 |"
#50000
0;
#55000
b101 ,
b101 T
b101 {
b101 ""
b1 >"
b1 #"
b101 $"
b101 !"
b1 j
b1 g
b0 }
b0 |
b0 a
b10 b
b10 _
1;
#56000
b10 e
b1 d
b1 8
b1 F
b1001 ?"
b1001 <"
b1001 5
b1001 C
b110 z
b110 4
b110 B
b11 Z
b11 3
b11 A
b11111111111111111111111111111111 }"
b10 ~"
b10 |"
#60000
0;
#65000
b11 e
b11 b
b11 _
b10 /
b10 W
b10 c
b10 h
b110 '"
b1 &"
b1 i
b10 j
b10 g
b1 r
b1 o
b0 ?"
b0 >"
b0 #"
b110 $"
b110 !"
b101 ,"
b101 )"
b1001 (
b1001 P
b1001 ="
b1001 B"
b1 ^"
b1 C"
b1001 D"
b1001 A"
1;
#66000
b0 e
b0 d
b0 8
b0 F
b1101 _"
b1101 \"
b1101 6
b1101 D
b1010 <"
b1010 5
b1010 C
b111 z
b111 4
b111 B
b100 Z
b100 3
b100 A
b0 }"
b11 ~"
b11 |"
#70000
0;
#75000
b1101 $
b1101 L
b1101 ]"
b1101 b"
b1 c"
b1101 d"
b1101 a"
b1001 L"
b1001 I"
b0 _"
b0 ^"
b0 C"
b1010 D"
b1010 A"
b101 4"
b101 1"
b110 +
b110 S
b110 %"
b110 *"
b1010 G"
b1 F"
b1 +"
b110 ,"
b110 )"
b111 $"
b111 !"
b1 w
b10 r
b10 o
b0 '"
b0 &"
b0 i
b11 j
b11 g
b100 b
b100 _
1;
#76000
b11 m
b1 l
b1 9
b1 G
b1110 \"
b1110 6
b1110 D
b1011 <"
b1011 5
b1011 C
b1000 z
b1000 4
b1000 B
b0 Z
b0 3
b0 A
b1 }"
b100 ~"
b100 |"
#80000
0;
#85000
b0 b
b0 _
b100 m
b100 j
b100 g
b11 .
b11 V
b11 k
b11 p
b111 /"
b1 ."
b1 q
b11 r
b11 o
b10 w
b1000 $"
b1000 !"
b0 F"
b0 +"
b111 ,"
b111 )"
b110 4"
b110 1"
b101 9"
b0 G"
b1011 D"
b1011 A"
b1010 '
b1010 O
b1010 E"
b1010 J"
b1110 g"
b1 f"
b1 K"
b1010 L"
b1010 I"
b1001 T"
b1001 Q"
b0 c"
b1110 d"
b1110 a"
b1101 l"
b1101 i"
1;
#86000
b0 m
b0 l
b0 9
b0 G
b1111 \"
b1111 6
b1111 D
b1100 <"
b1100 5
b1100 C
b0 z
b0 4
b0 B
b10 }"
b101 ~"
b101 |"
#90000
0;
#95000
b1101 t"
b1101 q"
b1110 #
b1110 K
b1110 e"
b1110 j"
b1 k"
b1110 l"
b1110 i"
b1111 d"
b1111 a"
b1001 Y"
b1010 T"
b1010 Q"
b0 g"
b0 f"
b0 K"
b1011 L"
b1011 I"
b1100 D"
b1100 A"
b110 9"
b111 *
b111 R
b111 -"
b111 2"
b1011 O"
b1 N"
b1 3"
b111 4"
b111 1"
b1000 ,"
b1000 )"
b0 $"
b0 !"
b11 w
b0 /"
b0 ."
b0 q
b100 r
b100 o
b0 j
b0 g
1;
#96000
b100 u
b1 t
b1 :
b1 H
b10000 \"
b10000 6
b10000 D
b0 <"
b0 5
b0 C
b11 }"
b110 ~"
b110 |"
#100000
0;
#105000
b0 u
b0 r
b0 o
b100 -
b100 U
b100 s
b100 x
b1000 7"
b1 6"
b1 y
b100 w
b0 ,"
b0 )"
b0 N"
b0 3"
b1000 4"
b1000 1"
b111 9"
b0 D"
b0 A"
b0 O"
b1100 L"
b1100 I"
b1011 &
b1011 N
b1011 M"
b1011 R"
b1111 o"
b1 n"
b1 S"
b1011 T"
b1011 Q"
b1010 Y"
b10000 d"
b10000 a"
b0 k"
b1111 l"
b1111 i"
b1110 t"
b1110 q"
b1101 y"
1;
#106000
b0 t
b0 :
b0 H
b0 \"
b0 6
b0 D
b100 }"
b111 ~"
b111 |"
#110000
0;
#115000
b1110 y"
b1111 "
b1111 J
b1111 m"
b1111 r"
b1 s"
b1111 t"
b1111 q"
b10000 l"
b10000 i"
b0 d"
b0 a"
b1011 Y"
b0 o"
b0 n"
b0 S"
b1100 T"
b1100 Q"
b0 L"
b0 I"
b1000 )
b1000 Q
b1000 5"
b1000 :"
b1100 W"
b1 V"
b1 ;"
b1000 9"
b0 4"
b0 1"
b0 7"
b0 6"
b0 y
b0 w
1;
#116000
b101 }"
b1000 ~"
b1000 |"
#120000
0;
